{
  "sounds": [
    {
      "name": "Baam Wow",
      "color": "#339900",
      "mp3": "sounds/baam_wow.mp3"
    },
    {
      "name": "Baka",
      "color": "#339900",
      "mp3": "sounds/baka.mp3"
    },
    {
      "name": "Hag Cackle",
      "color": "#339900",
      "mp3": "sounds/hag_cackle.mp3"
    },
    {
      "name": "He is gay!",
      "color": "#339900",
      "mp3": "sounds/he_is_gay.mp3"
    },
    {
      "name": "Honk Honk Awooga",
      "color": "#339900",
      "mp3": "sounds/honkhonk_awooga.mp3"
    },
    {
      "name": "Listen here you little shit",
      "color": "#339900",
      "mp3": "sounds/listen_here_you_little_shit.mp3"
    },
    {
      "name": "John Madden",
      "color": "#339900",
      "mp3": "sounds/nose_pinched_john_madden.mp3"
    },
    {
      "name": "Bleh",
      "color": "#339900",
      "mp3": "sounds/stick_out_tongue.mp3"
    },
    {
      "name": "That is disgusting",
      "color": "#339900",
      "mp3": "sounds/that_is_disgusting.mp3"
    },
    {
      "name": "That is disgusting (short)",
      "color": "#339900",
      "mp3": "sounds/that_is_disgusting_short.mp3"
    },
    {
      "name": "Urgh you are valid",
      "color": "#339900",
      "mp3": "sounds/urgh_you_are_valid.mp3"
    },
    {
      "name": "Wawawawawa",
      "color": "#339900",
      "mp3": "sounds/wawawawawa.mp3"
    }
  ]
}
